{
    "app": {
        "environment": "production"
    },
    "cloud": {
        "project_name": "neith-app-project",
        "credentials_path": "credentials.json",
        "firebase": {
            "apiKey": "teste",
            "authDomain": "neith-app-project.firebaseapp.com",
            "projectId": "neith-app-project",
            "storageBucket": "neith-app-project.appspot.com",
            "messagingSenderId": "18562248879",
            "appId": "1:18562248879:web:14678f224ebe100fbc645a",
            "measurementId": "teste"
        },
        "storage_bucket": "neith-app-project-places-photos-bucket-production"
    },
    "database": {
        "db_name": "neith-app-project-production"
    },
    "places_scraper": {
        "maps_api_key": "test-key",
        "maps_queries": [
            "restaurants",
            "historical landmarks",
            "nightclubs",
            "parks",
            "museums",
            "religious centers",
            "bars",
            "vegan restaurants",
            "vegetarian restaurants",
            "historical heritage",
            "malls",
            "craft fairs"
        ]
    }
}